agentry/__init__.py
agentry/cli.py
agentry/gui.py
agentry/mcp_client.py
agentry/reloader.py
agentry/session_manager.py
agentry/user_profile_manager.py
agentry/agents/__init__.py
agentry/agents/agent.py
agentry/agents/agent_basic.py
agentry/agents/agent_mcp.py
agentry/agents/agent_smart.py
agentry/agents/copilot.py
agentry/client/app.py
agentry/client/commands.py
agentry/client/display.py
agentry/client/input.py
agentry/config/__init__.py
agentry/config/prompts.py
agentry/config/settings.py
agentry/document_handlers/__init__.py
agentry/document_handlers/base.py
agentry/document_handlers/csv.py
agentry/document_handlers/docx.py
agentry/document_handlers/excel.py
agentry/document_handlers/image.py
agentry/document_handlers/pdf.py
agentry/document_handlers/pptx.py
agentry/document_handlers/registry.py
agentry/document_handlers/text.py
agentry/memory/__init__.py
agentry/memory/context_middleware.py
agentry/memory/middleware.py
agentry/memory/project_memory.py
agentry/memory/storage.py
agentry/memory/vfs.py
agentry/providers/__init__.py
agentry/providers/azure_provider.py
agentry/providers/base.py
agentry/providers/capability_detector.py
agentry/providers/capability_middleware.py
agentry/providers/gemini_provider.py
agentry/providers/groq_provider.py
agentry/providers/ollama_provider.py
agentry/providers/utils.py
agentry/services/__init__.py
agentry/services/marker_service.py
agentry/services/ollama_vision.py
agentry/tools/__init__.py
agentry/tools/agent_tools.py
agentry/tools/base.py
agentry/tools/convert_document.py
agentry/tools/document.py
agentry/tools/execution.py
agentry/tools/filesystem.py
agentry/tools/git.py
agentry/tools/office_tools.py
agentry/tools/pdf_tools.py
agentry/tools/registry.py
agentry/tools/web.py
agentry/ui/__init__.py
agentry/ui/server.py
agentry/utils/conversion.py
agentry_community-1.0.6.dist-info/licenses/LICENSE
agentry_community-1.0.6.dist-info/METADATA
agentry_community-1.0.6.dist-info/WHEEL
agentry_community-1.0.6.dist-info/entry_points.txt
agentry_community-1.0.6.dist-info/top_level.txt
agentry_community-1.0.6.dist-info/RECORD
