Metadata-Version: 2.4
Name: agentry_community
Version: 1.0.6
Summary: A modular AI agent framework built from scratch in Python, designed to evolve
Requires-Python: >=3.11
License-File: LICENSE
Requires-Dist: ddgs>=9.9.1
Requires-Dist: google>=3.0.0
Requires-Dist: google-api-python-client>=2.187.0
Requires-Dist: google-generativeai>=0.8.5
Requires-Dist: groq>=0.36.0
Requires-Dist: langchain-community>=0.4.1
Requires-Dist: mcp>=1.22.0
Requires-Dist: ollama>=0.6.1
Requires-Dist: py-toon-format>=0.1.0
Requires-Dist: pydantic>=2.12.4
Requires-Dist: requests>=2.32.5
Requires-Dist: textual>=6.7.1
Requires-Dist: watchdog>=6.0.0
Requires-Dist: pypdf>=5.1.0
Requires-Dist: python-docx>=1.1.2
Requires-Dist: python-pptx>=1.0.2
Requires-Dist: openpyxl>=3.1.5
Requires-Dist: fastapi>=0.124.2
Requires-Dist: uvicorn>=0.38.0
Requires-Dist: rich>=13.0.0
Requires-Dist: httpx>=0.27.0
Requires-Dist: anthropic
Dynamic: license-file
